[{"date":"11/23/2022","open":"$123.54"},{"date":"11/22/2022","open":"$120.84"},{"date":"11/21/2022","open":"$121.09"},{"date":"11/18/2022","open":"$124.04"},{"date":"11/17/2022","open":"$118.95"},{"date":"11/16/2022","open":"$123.2"},{"date":"11/15/2022","open":"$125.65"},{"date":"11/14/2022","open":"$120.74"},{"date":"11/11/2022","open":"$118.99"},{"date":"11/10/2022","open":"$115.91"},{"date":"11/09/2022","open":"$111.46"},{"date":"11/08/2022","open":"$111.57"},{"date":"11/07/2022","open":"$107.48"},{"date":"11/04/2022","open":"$106.61"},{"date":"11/03/2022","open":"$104.38"},{"date":"11/02/2022","open":"$118.71"},{"date":"11/01/2022","open":"$119.74"},{"date":"10/31/2022","open":"$118.13"},{"date":"10/28/2022","open":"$114.17"},{"date":"10/27/2022","open":"$119.315"},{"date":"10/26/2022","open":"$118.04"},{"date":"10/25/2022","open":"$116.57"},{"date":"10/24/2022","open":"$116.34"},{"date":"10/21/2022","open":"$111.75"},{"date":"10/20/2022","open":"$113.165"},{"date":"10/19/2022","open":"$110.86"},{"date":"10/18/2022","open":"$114.95"},{"date":"10/17/2022","open":"$113.92"},{"date":"10/14/2022","open":"$114.63"},{"date":"10/13/2022","open":"$105.38"},{"date":"10/12/2022","open":"$110.32"},{"date":"10/11/2022","open":"$112"},{"date":"10/10/2022","open":"$120.59"},{"date":"10/07/2022","open":"$122.62"},{"date":"10/06/2022","open":"$124.51"},{"date":"10/05/2022","open":"$120.88"},{"date":"10/04/2022","open":"$120.4"},{"date":"10/03/2022","open":"$114.99"},{"date":"09/30/2022","open":"$113.76"},{"date":"09/29/2022","open":"$117.28"},{"date":"09/28/2022","open":"$118.58"},{"date":"09/27/2022","open":"$121.56"},{"date":"09/26/2022","open":"$121.54"},{"date":"09/23/2022","open":"$122.34"},{"date":"09/22/2022","open":"$124.75"},{"date":"09/21/2022","open":"$125.44"},{"date":"09/20/2022","open":"$125.74"},{"date":"09/19/2022","open":"$123.62"},{"date":"09/16/2022","open":"$124.12"},{"date":"09/15/2022","open":"$126.7"},{"date":"09/14/2022","open":"$126.27"},{"date":"09/13/2022","open":"$128.38"},{"date":"09/12/2022","open":"$133"},{"date":"09/09/2022","open":"$130.68"},{"date":"09/08/2022","open":"$127.47"},{"date":"09/07/2022","open":"$127.47"},{"date":"09/06/2022","open":"$128.84"},{"date":"09/02/2022","open":"$131.64"},{"date":"09/01/2022","open":"$129.98"},{"date":"08/31/2022","open":"$133.79"},{"date":"08/30/2022","open":"$137.8"},{"date":"08/29/2022","open":"$137.81"},{"date":"08/26/2022","open":"$146.16"},{"date":"08/25/2022","open":"$142.34"},{"date":"08/24/2022","open":"$140.25"},{"date":"08/23/2022","open":"$142.09"},{"date":"08/22/2022","open":"$145.3"},{"date":"08/19/2022","open":"$149.29"},{"date":"08/18/2022","open":"$148.07"},{"date":"08/17/2022","open":"$148.23"},{"date":"08/16/2022","open":"$151.45"},{"date":"08/15/2022","open":"$150.32"},{"date":"08/12/2022","open":"$148"},{"date":"08/11/2022","open":"$148.31"},{"date":"08/10/2022","open":"$145.85"},{"date":"08/09/2022","open":"$145.59"},{"date":"08/08/2022","open":"$149.81"},{"date":"08/05/2022","open":"$148.57"},{"date":"08/04/2022","open":"$148.68"},{"date":"08/03/2022","open":"$147.66"},{"date":"08/02/2022","open":"$145.69"},{"date":"08/01/2022","open":"$144.31"},{"date":"07/29/2022","open":"$144.595"},{"date":"07/28/2022","open":"$149.78"},{"date":"07/27/2022","open":"$151.525"},{"date":"07/26/2022","open":"$152.62"},{"date":"07/25/2022","open":"$152.8"},{"date":"07/22/2022","open":"$155.66"},{"date":"07/21/2022","open":"$152.88"},{"date":"07/20/2022","open":"$147.43"},{"date":"07/19/2022","open":"$144.14"},{"date":"07/18/2022","open":"$145.97"},{"date":"07/15/2022","open":"$143.76"},{"date":"07/14/2022","open":"$134.94"},{"date":"07/13/2022","open":"$130.55"},{"date":"07/12/2022","open":"$133.74"},{"date":"07/11/2022","open":"$133.59"},{"date":"07/08/2022","open":"$132.52"},{"date":"07/07/2022","open":"$130.65"},{"date":"07/06/2022","open":"$126.06"},{"date":"07/05/2022","open":"$121.1"},{"date":"07/01/2022","open":"$125.75"},{"date":"06/30/2022","open":"$127.61"},{"date":"06/29/2022","open":"$130.08"},{"date":"06/28/2022","open":"$129.78"},{"date":"06/27/2022","open":"$126.2"},{"date":"06/24/2022","open":"$122.38"},{"date":"06/23/2022","open":"$122.75"},{"date":"06/22/2022","open":"$121.8"},{"date":"06/21/2022","open":"$123.77"},{"date":"06/17/2022","open":"$121.42"},{"date":"06/16/2022","open":"$126.26"},{"date":"06/15/2022","open":"$131.67"},{"date":"06/14/2022","open":"$130.21"},{"date":"06/13/2022","open":"$130.59"},{"date":"06/10/2022","open":"$134.75"},{"date":"06/09/2022","open":"$137.77"},{"date":"06/08/2022","open":"$140.746"},{"date":"06/07/2022","open":"$139.13"},{"date":"06/06/2022","open":"$144.95"},{"date":"06/03/2022","open":"$142.18"},{"date":"06/02/2022","open":"$140.26"},{"date":"06/01/2022","open":"$142.55"},{"date":"05/31/2022","open":"$139.5"},{"date":"05/27/2022","open":"$136.1"},{"date":"05/26/2022","open":"$130.01"},{"date":"05/25/2022","open":"$127.8"},{"date":"05/24/2022","open":"$130.34"},{"date":"05/23/2022","open":"$129.95"},{"date":"05/20/2022","open":"$132.88"},{"date":"05/19/2022","open":"$130.45"},{"date":"05/18/2022","open":"$136.83"},{"date":"05/17/2022","open":"$137.252"},{"date":"05/16/2022","open":"$133.98"},{"date":"05/13/2022","open":"$134.29"},{"date":"05/12/2022","open":"$131"},{"date":"05/11/2022","open":"$135.03"},{"date":"05/10/2022","open":"$139.5"},{"date":"05/09/2022","open":"$137.99"},{"date":"05/06/2022","open":"$141.248"},{"date":"05/05/2022","open":"$146.98"},{"date":"05/04/2022","open":"$144.58"},{"date":"05/03/2022","open":"$144.705"},{"date":"05/02/2022","open":"$140.6"},{"date":"04/29/2022","open":"$145.81"},{"date":"04/28/2022","open":"$142.87"},{"date":"04/27/2022","open":"$130.815"},{"date":"04/26/2022","open":"$135.02"},{"date":"04/25/2022","open":"$131.32"},{"date":"04/22/2022","open":"$136.13"},{"date":"04/21/2022","open":"$142.34"},{"date":"04/20/2022","open":"$143.21"},{"date":"04/19/2022","open":"$138.83"},{"date":"04/18/2022","open":"$135.62"},{"date":"04/14/2022","open":"$141.05"},{"date":"04/13/2022","open":"$137.54"},{"date":"04/12/2022","open":"$137.92"},{"date":"04/11/2022","open":"$134.292"},{"date":"04/08/2022","open":"$138.54"},{"date":"04/07/2022","open":"$139.79"},{"date":"04/06/2022","open":"$142.9"},{"date":"04/05/2022","open":"$151.81"},{"date":"04/04/2022","open":"$147.74"},{"date":"04/01/2022","open":"$151.94"},{"date":"03/31/2022","open":"$152.885"},{"date":"03/30/2022","open":"$159.39"},{"date":"03/29/2022","open":"$161.21"},{"date":"03/28/2022","open":"$156.5"},{"date":"03/25/2022","open":"$157.97"},{"date":"03/24/2022","open":"$154.3"},{"date":"03/23/2022","open":"$156.11"},{"date":"03/22/2022","open":"$155.45"},{"date":"03/21/2022","open":"$153.99"},{"date":"03/18/2022","open":"$152.52"},{"date":"03/17/2022","open":"$149.19"},{"date":"03/16/2022","open":"$146.965"},{"date":"03/15/2022","open":"$142.5"},{"date":"03/14/2022","open":"$150.8"},{"date":"03/11/2022","open":"$157.95"},{"date":"03/10/2022","open":"$154.04"},{"date":"03/09/2022","open":"$156.01"},{"date":"03/08/2022","open":"$150.66"},{"date":"03/07/2022","open":"$162.32"},{"date":"03/04/2022","open":"$163.85"},{"date":"03/03/2022","open":"$170.67"},{"date":"03/02/2022","open":"$165.25"},{"date":"03/01/2022","open":"$170.96"},{"date":"02/28/2022","open":"$168.3"},{"date":"02/25/2022","open":"$167.61"},{"date":"02/24/2022","open":"$156.89"},{"date":"02/23/2022","open":"$166.65"},{"date":"02/22/2022","open":"$164.059"},{"date":"02/18/2022","open":"$167.47"},{"date":"02/17/2022","open":"$169.875"},{"date":"02/16/2022","open":"$170.68"},{"date":"02/15/2022","open":"$169"},{"date":"02/14/2022","open":"$165.35"},{"date":"02/11/2022","open":"$174.7"},{"date":"02/10/2022","open":"$179.4"},{"date":"02/09/2022","open":"$181.4"},{"date":"02/08/2022","open":"$174.305"},{"date":"02/07/2022","open":"$179.665"},{"date":"02/04/2022","open":"$178.99"},{"date":"02/03/2022","open":"$180.8"},{"date":"02/02/2022","open":"$180.94"},{"date":"02/01/2022","open":"$176.4447"},{"date":"01/31/2022","open":"$167.06"},{"date":"01/28/2022","open":"$162.01"},{"date":"01/27/2022","open":"$169.31"},{"date":"01/26/2022","open":"$168.58"},{"date":"01/25/2022","open":"$166.17"},{"date":"01/24/2022","open":"$162.18"},{"date":"01/21/2022","open":"$166.24"},{"date":"01/20/2022","open":"$174.53"},{"date":"01/19/2022","open":"$180.57"},{"date":"01/18/2022","open":"$185.87"},{"date":"01/14/2022","open":"$182.8"},{"date":"01/13/2022","open":"$188.7"},{"date":"01/12/2022","open":"$186.6"},{"date":"01/11/2022","open":"$179.19"},{"date":"01/10/2022","open":"$178.27"},{"date":"01/07/2022","open":"$186.6"},{"date":"01/06/2022","open":"$184.52"},{"date":"01/05/2022","open":"$186.5"},{"date":"01/04/2022","open":"$187"},{"date":"01/03/2022","open":"$182.91"},{"date":"12/31/2021","open":"$183.31"},{"date":"12/30/2021","open":"$185.88"},{"date":"12/29/2021","open":"$184.685"},{"date":"12/28/2021","open":"$186.59"},{"date":"12/27/2021","open":"$183.21"},{"date":"12/23/2021","open":"$181.53"},{"date":"12/22/2021","open":"$179"},{"date":"12/21/2021","open":"$179.38"},{"date":"12/20/2021","open":"$174.29"},{"date":"12/17/2021","open":"$175.725"},{"date":"12/16/2021","open":"$190.304"},{"date":"12/15/2021","open":"$183.97"},{"date":"12/14/2021","open":"$181.2"},{"date":"12/13/2021","open":"$186.85"},{"date":"12/10/2021","open":"$185.55"},{"date":"12/09/2021","open":"$181.77"},{"date":"12/08/2021","open":"$183.01"},{"date":"12/07/2021","open":"$179.07"},{"date":"12/06/2021","open":"$176.88"},{"date":"12/03/2021","open":"$178.04"},{"date":"12/02/2021","open":"$172.09"},{"date":"12/01/2021","open":"$180.885"},{"date":"11/30/2021","open":"$183.22"},{"date":"11/29/2021","open":"$179.48"},{"date":"11/26/2021","open":"$175.665"},{"date":"11/24/2021","open":"$179.52"},{"date":"11/23/2021","open":"$180.34"},{"date":"11/22/2021","open":"$181.11"},{"date":"11/19/2021","open":"$184.69"},{"date":"11/18/2021","open":"$185.24"},{"date":"11/17/2021","open":"$180.79"},{"date":"11/16/2021","open":"$168.11"},{"date":"11/15/2021","open":"$166.5"},{"date":"11/12/2021","open":"$165"},{"date":"11/11/2021","open":"$161.8"},{"date":"11/10/2021","open":"$165.09"},{"date":"11/09/2021","open":"$166.51"},{"date":"11/08/2021","open":"$163.21"},{"date":"11/05/2021","open":"$157.075"},{"date":"11/04/2021","open":"$156.325"},{"date":"11/03/2021","open":"$135.75"},{"date":"11/02/2021","open":"$134.55"},{"date":"11/01/2021","open":"$132.44"},{"date":"10/29/2021","open":"$132.862"},{"date":"10/28/2021","open":"$131.99"},{"date":"10/27/2021","open":"$131.94"},{"date":"10/26/2021","open":"$132.9"},{"date":"10/25/2021","open":"$131.82"},{"date":"10/22/2021","open":"$132.9"},{"date":"10/21/2021","open":"$132"},{"date":"10/20/2021","open":"$132.5"},{"date":"10/19/2021","open":"$131.017"},{"date":"10/18/2021","open":"$129.32"},{"date":"10/15/2021","open":"$129.02"},{"date":"10/14/2021","open":"$126.16"},{"date":"10/13/2021","open":"$125.2"},{"date":"10/12/2021","open":"$125.38"},{"date":"10/11/2021","open":"$126.055"},{"date":"10/08/2021","open":"$128.5912"},{"date":"10/07/2021","open":"$129.265"},{"date":"10/06/2021","open":"$126.55"},{"date":"10/05/2021","open":"$126.13"},{"date":"10/04/2021","open":"$128.92"},{"date":"10/01/2021","open":"$129.8"},{"date":"09/30/2021","open":"$130.35"},{"date":"09/29/2021","open":"$130.59"},{"date":"09/28/2021","open":"$131.75"},{"date":"09/27/2021","open":"$132.43"},{"date":"09/24/2021","open":"$133.11"},{"date":"09/23/2021","open":"$133.75"},{"date":"09/22/2021","open":"$132.59"},{"date":"09/21/2021","open":"$133.587"},{"date":"09/20/2021","open":"$131.47"},{"date":"09/17/2021","open":"$137.81"},{"date":"09/16/2021","open":"$137.32"},{"date":"09/15/2021","open":"$140.805"},{"date":"09/14/2021","open":"$144.47"},{"date":"09/13/2021","open":"$144.02"},{"date":"09/10/2021","open":"$143.13"},{"date":"09/09/2021","open":"$142.47"},{"date":"09/08/2021","open":"$143.36"},{"date":"09/07/2021","open":"$144.675"},{"date":"09/03/2021","open":"$145.12"},{"date":"09/02/2021","open":"$146.7"},{"date":"09/01/2021","open":"$146.84"},{"date":"08/31/2021","open":"$146.8"},{"date":"08/30/2021","open":"$145.59"},{"date":"08/27/2021","open":"$142.2"},{"date":"08/26/2021","open":"$143.19"},{"date":"08/25/2021","open":"$144.46"},{"date":"08/24/2021","open":"$144.59"},{"date":"08/23/2021","open":"$142.653"},{"date":"08/20/2021","open":"$140.61"},{"date":"08/19/2021","open":"$140.65"},{"date":"08/18/2021","open":"$143.84"},{"date":"08/17/2021","open":"$146.95"},{"date":"08/16/2021","open":"$148.4"},{"date":"08/13/2021","open":"$147"},{"date":"08/12/2021","open":"$147.76"},{"date":"08/11/2021","open":"$146.06"},{"date":"08/10/2021","open":"$147.32"},{"date":"08/09/2021","open":"$146.79"},{"date":"08/06/2021","open":"$146.13"},{"date":"08/05/2021","open":"$147.24"},{"date":"08/04/2021","open":"$148.02"},{"date":"08/03/2021","open":"$148.91"},{"date":"08/02/2021","open":"$150"},{"date":"07/30/2021","open":"$149.2"},{"date":"07/29/2021","open":"$146.5"},{"date":"07/28/2021","open":"$141.27"},{"date":"07/27/2021","open":"$142.49"},{"date":"07/26/2021","open":"$143.95"},{"date":"07/23/2021","open":"$143.45"},{"date":"07/22/2021","open":"$142"},{"date":"07/21/2021","open":"$139.65"},{"date":"07/20/2021","open":"$139.02"},{"date":"07/19/2021","open":"$138.325"},{"date":"07/16/2021","open":"$141.87"},{"date":"07/15/2021","open":"$144.12"},{"date":"07/14/2021","open":"$143.5"},{"date":"07/13/2021","open":"$142.44"},{"date":"07/12/2021","open":"$141.4"},{"date":"07/09/2021","open":"$137.89"},{"date":"07/08/2021","open":"$137.72"},{"date":"07/07/2021","open":"$142.24"},{"date":"07/06/2021","open":"$143"},{"date":"07/02/2021","open":"$141.99"},{"date":"07/01/2021","open":"$142.91"},{"date":"06/30/2021","open":"$142.35"},{"date":"06/29/2021","open":"$139.632"},{"date":"06/28/2021","open":"$138.23"},{"date":"06/25/2021","open":"$138.45"},{"date":"06/24/2021","open":"$136.619"},{"date":"06/23/2021","open":"$134.89"},{"date":"06/22/2021","open":"$134.22"},{"date":"06/21/2021","open":"$133.05"},{"date":"06/18/2021","open":"$134.55"},{"date":"06/17/2021","open":"$134.31"},{"date":"06/16/2021","open":"$136.47"},{"date":"06/15/2021","open":"$137.14"},{"date":"06/14/2021","open":"$135.195"},{"date":"06/11/2021","open":"$133.8"},{"date":"06/10/2021","open":"$133.05"},{"date":"06/09/2021","open":"$135.105"},{"date":"06/08/2021","open":"$134.06"},{"date":"06/07/2021","open":"$133.7"},{"date":"06/04/2021","open":"$132.525"},{"date":"06/03/2021","open":"$132.65"},{"date":"06/02/2021","open":"$133.18"},{"date":"06/01/2021","open":"$135.104"},{"date":"05/28/2021","open":"$134.154"},{"date":"05/27/2021","open":"$132.73"},{"date":"05/26/2021","open":"$133.87"},{"date":"05/25/2021","open":"$133.54"},{"date":"05/24/2021","open":"$131.33"},{"date":"05/21/2021","open":"$132.14"},{"date":"05/20/2021","open":"$131.529"},{"date":"05/19/2021","open":"$127.185"},{"date":"05/18/2021","open":"$130.64"},{"date":"05/17/2021","open":"$129.29"},{"date":"05/14/2021","open":"$128.63"},{"date":"05/13/2021","open":"$127.12"},{"date":"05/12/2021","open":"$126.029"},{"date":"05/11/2021","open":"$125.25"},{"date":"05/10/2021","open":"$136.02"},{"date":"05/07/2021","open":"$136.937"},{"date":"05/06/2021","open":"$134.49"},{"date":"05/05/2021","open":"$136.08"},{"date":"05/04/2021","open":"$136"},{"date":"05/03/2021","open":"$139.7"},{"date":"04/30/2021","open":"$141.07"},{"date":"04/29/2021","open":"$145.01"},{"date":"04/28/2021","open":"$138.17"},{"date":"04/27/2021","open":"$138.71"},{"date":"04/26/2021","open":"$135.33"},{"date":"04/23/2021","open":"$133.74"},{"date":"04/22/2021","open":"$135.37"},{"date":"04/21/2021","open":"$132.82"},{"date":"04/20/2021","open":"$134.55"},{"date":"04/19/2021","open":"$136.9"},{"date":"04/16/2021","open":"$137.62"},{"date":"04/15/2021","open":"$136"},{"date":"04/14/2021","open":"$137.08"},{"date":"04/13/2021","open":"$138.38"},{"date":"04/12/2021","open":"$138.86"},{"date":"04/09/2021","open":"$139.904"},{"date":"04/08/2021","open":"$140"},{"date":"04/07/2021","open":"$138.33"},{"date":"04/06/2021","open":"$139.85"},{"date":"04/05/2021","open":"$139.04"},{"date":"04/01/2021","open":"$134.5"},{"date":"03/31/2021","open":"$130.96"},{"date":"03/30/2021","open":"$130.17"},{"date":"03/29/2021","open":"$132.54"},{"date":"03/26/2021","open":"$127.06"},{"date":"03/25/2021","open":"$126.66"},{"date":"03/24/2021","open":"$132.99"},{"date":"03/23/2021","open":"$134"},{"date":"03/22/2021","open":"$132.96"},{"date":"03/19/2021","open":"$129.79"},{"date":"03/18/2021","open":"$132.44"},{"date":"03/17/2021","open":"$131.31"},{"date":"03/16/2021","open":"$132.89"},{"date":"03/15/2021","open":"$130.06"},{"date":"03/12/2021","open":"$129.9"},{"date":"03/11/2021","open":"$131.01"},{"date":"03/10/2021","open":"$130.67"},{"date":"03/09/2021","open":"$127.385"},{"date":"03/08/2021","open":"$129"},{"date":"03/05/2021","open":"$130.92"},{"date":"03/04/2021","open":"$132.35"},{"date":"03/03/2021","open":"$135.6"},{"date":"03/02/2021","open":"$140"},{"date":"03/01/2021","open":"$137.5"},{"date":"02/26/2021","open":"$136.76"},{"date":"02/25/2021","open":"$139.56"},{"date":"02/24/2021","open":"$136.4"},{"date":"02/23/2021","open":"$136.38"},{"date":"02/22/2021","open":"$142.25"},{"date":"02/19/2021","open":"$144.78"},{"date":"02/18/2021","open":"$143.54"},{"date":"02/17/2021","open":"$145.825"},{"date":"02/16/2021","open":"$149"},{"date":"02/12/2021","open":"$145.57"},{"date":"02/11/2021","open":"$145.78"},{"date":"02/10/2021","open":"$147.62"},{"date":"02/09/2021","open":"$147.55"},{"date":"02/08/2021","open":"$147.1"},{"date":"02/05/2021","open":"$148.85"},{"date":"02/04/2021","open":"$150.18"},{"date":"02/03/2021","open":"$167.577"},{"date":"02/02/2021","open":"$164.51"},{"date":"02/01/2021","open":"$157.37"},{"date":"01/29/2021","open":"$160.247"},{"date":"01/28/2021","open":"$156.28"},{"date":"01/27/2021","open":"$158.49"},{"date":"01/26/2021","open":"$164.2"},{"date":"01/25/2021","open":"$164.32"},{"date":"01/22/2021","open":"$164"},{"date":"01/21/2021","open":"$165.805"},{"date":"01/20/2021","open":"$164.72"},{"date":"01/19/2021","open":"$158.94"},{"date":"01/15/2021","open":"$160.77"},{"date":"01/14/2021","open":"$159.397"},{"date":"01/13/2021","open":"$155.19"},{"date":"01/12/2021","open":"$156.64"},{"date":"01/11/2021","open":"$156.1"},{"date":"01/08/2021","open":"$157.23"},{"date":"01/07/2021","open":"$152.33"},{"date":"01/06/2021","open":"$151.53"},{"date":"01/05/2021","open":"$148.65"},{"date":"01/04/2021","open":"$153.01"},{"date":"12/31/2020","open":"$150.322"},{"date":"12/30/2020","open":"$149.12"},{"date":"12/29/2020","open":"$148.97"},{"date":"12/28/2020","open":"$150.62"},{"date":"12/24/2020","open":"$147.8"},{"date":"12/23/2020","open":"$147.63"},{"date":"12/22/2020","open":"$146.611"},{"date":"12/21/2020","open":"$145.005"},{"date":"12/18/2020","open":"$150.7947"},{"date":"12/17/2020","open":"$150.865"},{"date":"12/16/2020","open":"$149.14"},{"date":"12/15/2020","open":"$149.37"},{"date":"12/14/2020","open":"$144.9"},{"date":"12/11/2020","open":"$149.24"},{"date":"12/10/2020","open":"$154.42"},{"date":"12/09/2020","open":"$158.6"},{"date":"12/08/2020","open":"$157.46"},{"date":"12/07/2020","open":"$158.55"},{"date":"12/04/2020","open":"$150.3"},{"date":"12/03/2020","open":"$151.04"},{"date":"12/02/2020","open":"$150.51"},{"date":"12/01/2020","open":"$148.79"},{"date":"11/30/2020","open":"$144.63"},{"date":"11/27/2020","open":"$145.49"},{"date":"11/25/2020","open":"$145.95"},{"date":"11/24/2020","open":"$143.39"},{"date":"11/23/2020","open":"$142.35"},{"date":"11/20/2020","open":"$148.28"},{"date":"11/19/2020","open":"$146.561"},{"date":"11/18/2020","open":"$149.24"},{"date":"11/17/2020","open":"$149.02"},{"date":"11/16/2020","open":"$145.2"},{"date":"11/13/2020","open":"$145.538"},{"date":"11/12/2020","open":"$147.57"},{"date":"11/11/2020","open":"$144.5"},{"date":"11/10/2020","open":"$140.148"},{"date":"11/09/2020","open":"$149.41"},{"date":"11/06/2020","open":"$146.01"},{"date":"11/05/2020","open":"$145.819"},{"date":"11/04/2020","open":"$129.325"},{"date":"11/03/2020","open":"$125.44"},{"date":"11/02/2020","open":"$124.5"},{"date":"10/30/2020","open":"$123.68"},{"date":"10/29/2020","open":"$122.06"},{"date":"10/28/2020","open":"$123.5"},{"date":"10/27/2020","open":"$126.51"},{"date":"10/26/2020","open":"$127.53"},{"date":"10/23/2020","open":"$128.59"},{"date":"10/22/2020","open":"$129.51"},{"date":"10/21/2020","open":"$128.04"},{"date":"10/20/2020","open":"$129.18"},{"date":"10/19/2020","open":"$130.127"},{"date":"10/16/2020","open":"$129.7"},{"date":"10/15/2020","open":"$127.3"},{"date":"10/14/2020","open":"$129.08"},{"date":"10/13/2020","open":"$127.47"},{"date":"10/12/2020","open":"$127.6996"},{"date":"10/09/2020","open":"$123.93"},{"date":"10/08/2020","open":"$124"},{"date":"10/07/2020","open":"$121.235"},{"date":"10/06/2020","open":"$120.45"},{"date":"10/05/2020","open":"$116.9"},{"date":"10/02/2020","open":"$116.78"},{"date":"10/01/2020","open":"$119.93"},{"date":"09/30/2020","open":"$117.5"},{"date":"09/29/2020","open":"$118.14"},{"date":"09/28/2020","open":"$115.96"},{"date":"09/25/2020","open":"$113.55"},{"date":"09/24/2020","open":"$109.39"},{"date":"09/23/2020","open":"$113.64"},{"date":"09/22/2020","open":"$112.61"},{"date":"09/21/2020","open":"$109.16"},{"date":"09/18/2020","open":"$115.04"},{"date":"09/17/2020","open":"$111.92"},{"date":"09/16/2020","open":"$118"},{"date":"09/15/2020","open":"$114.94"},{"date":"09/14/2020","open":"$115.24"},{"date":"09/11/2020","open":"$113.38"},{"date":"09/10/2020","open":"$115.15"},{"date":"09/09/2020","open":"$113.48"},{"date":"09/08/2020","open":"$111.94"},{"date":"09/04/2020","open":"$115.69"},{"date":"09/03/2020","open":"$121.3"},{"date":"09/02/2020","open":"$123.26"},{"date":"09/01/2020","open":"$121.08"},{"date":"08/31/2020","open":"$118.332"},{"date":"08/28/2020","open":"$116.71"},{"date":"08/27/2020","open":"$116.43"},{"date":"08/26/2020","open":"$116.25"},{"date":"08/25/2020","open":"$116.11"},{"date":"08/24/2020","open":"$114.37"},{"date":"08/21/2020","open":"$110.23"},{"date":"08/20/2020","open":"$110"},{"date":"08/19/2020","open":"$112.33"},{"date":"08/18/2020","open":"$112.91"},{"date":"08/17/2020","open":"$113.29"},{"date":"08/14/2020","open":"$113.3"},{"date":"08/13/2020","open":"$116.2"},{"date":"08/12/2020","open":"$110.39"},{"date":"08/11/2020","open":"$106.2"},{"date":"08/10/2020","open":"$108.6"},{"date":"08/07/2020","open":"$110.01"},{"date":"08/06/2020","open":"$111.23"},{"date":"08/05/2020","open":"$111"},{"date":"08/04/2020","open":"$109.49"},{"date":"08/03/2020","open":"$107.4"},{"date":"07/31/2020","open":"$105.66"},{"date":"07/30/2020","open":"$102.42"},{"date":"07/29/2020","open":"$92.08"},{"date":"07/28/2020","open":"$92.171"},{"date":"07/27/2020","open":"$90.023"},{"date":"07/24/2020","open":"$89.21"},{"date":"07/23/2020","open":"$92.91"},{"date":"07/22/2020","open":"$92.74"},{"date":"07/21/2020","open":"$93.55"},{"date":"07/20/2020","open":"$92.192"},{"date":"07/17/2020","open":"$91.68"},{"date":"07/16/2020","open":"$91.264"},{"date":"07/15/2020","open":"$92.93"},{"date":"07/14/2020","open":"$90.86"},{"date":"07/13/2020","open":"$93.3"},{"date":"07/10/2020","open":"$93"},{"date":"07/09/2020","open":"$93.95"},{"date":"07/08/2020","open":"$93.27"},{"date":"07/07/2020","open":"$92.97"},{"date":"07/06/2020","open":"$93.21"},{"date":"07/02/2020","open":"$91.09"},{"date":"07/01/2020","open":"$91.01"},{"date":"06/30/2020","open":"$89.2"},{"date":"06/29/2020","open":"$88.211"},{"date":"06/26/2020","open":"$89.07"},{"date":"06/25/2020","open":"$88.7"},{"date":"06/24/2020","open":"$89.175"},{"date":"06/23/2020","open":"$90.14"},{"date":"06/22/2020","open":"$88.72"},{"date":"06/19/2020","open":"$89.87"},{"date":"06/18/2020","open":"$89.85"},{"date":"06/17/2020","open":"$90.68"},{"date":"06/16/2020","open":"$89.9"},{"date":"06/15/2020","open":"$83.67"},{"date":"06/12/2020","open":"$86.25"},{"date":"06/11/2020","open":"$88.62"},{"date":"06/10/2020","open":"$90.25"},{"date":"06/09/2020","open":"$90.23"},{"date":"06/08/2020","open":"$89"},{"date":"06/05/2020","open":"$88"},{"date":"06/04/2020","open":"$83.95"},{"date":"06/03/2020","open":"$84.95"},{"date":"06/02/2020","open":"$79.93"},{"date":"06/01/2020","open":"$79.89"},{"date":"05/29/2020","open":"$78.7"},{"date":"05/28/2020","open":"$80.24"},{"date":"05/27/2020","open":"$78.27"},{"date":"05/26/2020","open":"$80.19"},{"date":"05/22/2020","open":"$78.26"},{"date":"05/21/2020","open":"$79.47"},{"date":"05/20/2020","open":"$79.96"},{"date":"05/19/2020","open":"$79.75"},{"date":"05/18/2020","open":"$77.27"},{"date":"05/15/2020","open":"$74.67"},{"date":"05/14/2020","open":"$77.5"},{"date":"05/13/2020","open":"$78.86"},{"date":"05/12/2020","open":"$81.29"},{"date":"05/11/2020","open":"$80.29"},{"date":"05/08/2020","open":"$79.7"},{"date":"05/07/2020","open":"$79.7"},{"date":"05/06/2020","open":"$78.81"},{"date":"05/05/2020","open":"$76.75"},{"date":"05/04/2020","open":"$75.16"},{"date":"05/01/2020","open":"$76.85"},{"date":"04/30/2020","open":"$80.27"},{"date":"04/29/2020","open":"$77.17"},{"date":"04/28/2020","open":"$77.108"},{"date":"04/27/2020","open":"$76.59"},{"date":"04/24/2020","open":"$73.92"},{"date":"04/23/2020","open":"$75"},{"date":"04/22/2020","open":"$73.79"},{"date":"04/21/2020","open":"$73.31"},{"date":"04/20/2020","open":"$75.022"},{"date":"04/17/2020","open":"$77.32"},{"date":"04/16/2020","open":"$76.86"},{"date":"04/15/2020","open":"$75.864"},{"date":"04/14/2020","open":"$75"},{"date":"04/13/2020","open":"$71.71"},{"date":"04/09/2020","open":"$74.62"},{"date":"04/08/2020","open":"$73.7"},{"date":"04/07/2020","open":"$73.66"},{"date":"04/06/2020","open":"$68.5"},{"date":"04/03/2020","open":"$67.68"},{"date":"04/02/2020","open":"$65.87"},{"date":"04/01/2020","open":"$65"},{"date":"03/31/2020","open":"$69.3"},{"date":"03/30/2020","open":"$67.19"},{"date":"03/27/2020","open":"$66.5"},{"date":"03/26/2020","open":"$64"},{"date":"03/25/2020","open":"$65.9"},{"date":"03/24/2020","open":"$66"},{"date":"03/23/2020","open":"$61.55"},{"date":"03/20/2020","open":"$65.03"},{"date":"03/19/2020","open":"$61.12"},{"date":"03/18/2020","open":"$63.56"},{"date":"03/17/2020","open":"$65.91"},{"date":"03/16/2020","open":"$68.28"},{"date":"03/13/2020","open":"$71.18"},{"date":"03/12/2020","open":"$69.52"},{"date":"03/11/2020","open":"$76.29"},{"date":"03/10/2020","open":"$74.8"},{"date":"03/09/2020","open":"$72.4"},{"date":"03/06/2020","open":"$76.33"},{"date":"03/05/2020","open":"$79.46"},{"date":"03/04/2020","open":"$79.12"},{"date":"03/03/2020","open":"$80.82"},{"date":"03/02/2020","open":"$79.015"},{"date":"02/28/2020","open":"$73.76"},{"date":"02/27/2020","open":"$77.13"},{"date":"02/26/2020","open":"$81"},{"date":"02/25/2020","open":"$83.94"},{"date":"02/24/2020","open":"$83.9"},{"date":"02/21/2020","open":"$88.56"},{"date":"02/20/2020","open":"$90.81"},{"date":"02/19/2020","open":"$88.92"},{"date":"02/18/2020","open":"$87.83"},{"date":"02/14/2020","open":"$90.55"},{"date":"02/13/2020","open":"$91.03"},{"date":"02/12/2020","open":"$91.65"},{"date":"02/11/2020","open":"$89.37"},{"date":"02/10/2020","open":"$86.78"},{"date":"02/07/2020","open":"$89.62"},{"date":"02/06/2020","open":"$88.06"},{"date":"02/05/2020","open":"$90.99"},{"date":"02/04/2020","open":"$88.25"},{"date":"02/03/2020","open":"$85.55"},{"date":"01/31/2020","open":"$87.05"},{"date":"01/30/2020","open":"$87.31"},{"date":"01/29/2020","open":"$88.66"},{"date":"01/28/2020","open":"$88.15"},{"date":"01/27/2020","open":"$87.304"},{"date":"01/24/2020","open":"$92.68"},{"date":"01/23/2020","open":"$92.85"},{"date":"01/22/2020","open":"$95.26"},{"date":"01/21/2020","open":"$95.33"},{"date":"01/17/2020","open":"$93"},{"date":"01/16/2020","open":"$90.22"},{"date":"01/15/2020","open":"$90.75"},{"date":"01/14/2020","open":"$91.13"},{"date":"01/13/2020","open":"$91.05"},{"date":"01/10/2020","open":"$90.51"},{"date":"01/09/2020","open":"$89.66"},{"date":"01/08/2020","open":"$88.9"},{"date":"01/07/2020","open":"$87.04"},{"date":"01/06/2020","open":"$85.91"},{"date":"01/03/2020","open":"$87.26"},{"date":"01/02/2020","open":"$89.05"},{"date":"12/31/2019","open":"$87.99"},{"date":"12/30/2019","open":"$88.71"},{"date":"12/27/2019","open":"$88.9"},{"date":"12/26/2019","open":"$88.92"},{"date":"12/24/2019","open":"$88.62"},{"date":"12/23/2019","open":"$89.01"},{"date":"12/20/2019","open":"$88.82"},{"date":"12/19/2019","open":"$88.36"},{"date":"12/18/2019","open":"$88.54"},{"date":"12/17/2019","open":"$89"},{"date":"12/16/2019","open":"$89.28"},{"date":"12/13/2019","open":"$88.91"},{"date":"12/12/2019","open":"$86.84"},{"date":"12/11/2019","open":"$84.84"},{"date":"12/10/2019","open":"$85.04"},{"date":"12/09/2019","open":"$84"},{"date":"12/06/2019","open":"$83.45"},{"date":"12/05/2019","open":"$82.65"},{"date":"12/04/2019","open":"$80.92"},{"date":"12/03/2019","open":"$81.38"},{"date":"12/02/2019","open":"$83.98"},{"date":"11/29/2019","open":"$84.51"},{"date":"11/27/2019","open":"$85.16"},{"date":"11/26/2019","open":"$85.25"},{"date":"11/25/2019","open":"$85.76"},{"date":"11/22/2019","open":"$85.29"},{"date":"11/21/2019","open":"$84.79"},{"date":"11/20/2019","open":"$87.82"},{"date":"11/19/2019","open":"$91.25"},{"date":"11/18/2019","open":"$90.81"},{"date":"11/15/2019","open":"$92.6"},{"date":"11/14/2019","open":"$90.31"},{"date":"11/13/2019","open":"$90.7"},{"date":"11/12/2019","open":"$92.18"},{"date":"11/11/2019","open":"$91.71"},{"date":"11/08/2019","open":"$89.98"},{"date":"11/07/2019","open":"$89.83"},{"date":"11/06/2019","open":"$85.34"},{"date":"11/05/2019","open":"$85.2"},{"date":"11/04/2019","open":"$84.54"},{"date":"11/01/2019","open":"$81.59"},{"date":"10/31/2019","open":"$81.44"},{"date":"10/30/2019","open":"$82.1"},{"date":"10/29/2019","open":"$82.75"},{"date":"10/28/2019","open":"$80.55"},{"date":"10/25/2019","open":"$79"},{"date":"10/24/2019","open":"$78.06"},{"date":"10/23/2019","open":"$77.21"},{"date":"10/22/2019","open":"$78.93"},{"date":"10/21/2019","open":"$78.38"},{"date":"10/18/2019","open":"$78.62"},{"date":"10/17/2019","open":"$78.7"},{"date":"10/16/2019","open":"$77.49"},{"date":"10/15/2019","open":"$76.88"},{"date":"10/14/2019","open":"$76.65"},{"date":"10/11/2019","open":"$76.19"},{"date":"10/10/2019","open":"$74.35"},{"date":"10/09/2019","open":"$73.91"},{"date":"10/08/2019","open":"$75.52"},{"date":"10/07/2019","open":"$77.01"},{"date":"10/04/2019","open":"$76.32"},{"date":"10/03/2019","open":"$73.93"},{"date":"10/02/2019","open":"$75.26"},{"date":"10/01/2019","open":"$77.06"},{"date":"09/30/2019","open":"$76.89"},{"date":"09/27/2019","open":"$77.01"},{"date":"09/26/2019","open":"$77.16"},{"date":"09/25/2019","open":"$75.03"},{"date":"09/24/2019","open":"$78.08"},{"date":"09/23/2019","open":"$76.67"},{"date":"09/20/2019","open":"$78.2"},{"date":"09/19/2019","open":"$79.24"},{"date":"09/18/2019","open":"$78.69"},{"date":"09/17/2019","open":"$77.61"},{"date":"09/16/2019","open":"$77.58"},{"date":"09/13/2019","open":"$79.18"},{"date":"09/12/2019","open":"$80.05"},{"date":"09/11/2019","open":"$78.17"},{"date":"09/10/2019","open":"$78.03"},{"date":"09/09/2019","open":"$79.04"},{"date":"09/06/2019","open":"$78.96"},{"date":"09/05/2019","open":"$77.89"},{"date":"09/04/2019","open":"$75.99"},{"date":"09/03/2019","open":"$76.77"},{"date":"08/30/2019","open":"$77.18"},{"date":"08/29/2019","open":"$75.22"},{"date":"08/28/2019","open":"$73.79"},{"date":"08/27/2019","open":"$73.68"},{"date":"08/26/2019","open":"$74.9"},{"date":"08/23/2019","open":"$76.12"},{"date":"08/22/2019","open":"$76.91"},{"date":"08/21/2019","open":"$76.5"},{"date":"08/20/2019","open":"$74.57"},{"date":"08/19/2019","open":"$74.58"},{"date":"08/16/2019","open":"$71.85"},{"date":"08/15/2019","open":"$71.44"},{"date":"08/14/2019","open":"$70.64"},{"date":"08/13/2019","open":"$69.89"},{"date":"08/12/2019","open":"$71"},{"date":"08/09/2019","open":"$70.51"},{"date":"08/08/2019","open":"$69.56"},{"date":"08/07/2019","open":"$67.26"},{"date":"08/06/2019","open":"$69.52"},{"date":"08/05/2019","open":"$69.97"},{"date":"08/02/2019","open":"$70.44"},{"date":"08/01/2019","open":"$68.88"},{"date":"07/31/2019","open":"$74.83"},{"date":"07/30/2019","open":"$74.58"},{"date":"07/29/2019","open":"$75.16"},{"date":"07/26/2019","open":"$75.11"},{"date":"07/25/2019","open":"$75.84"},{"date":"07/24/2019","open":"$74.01"},{"date":"07/23/2019","open":"$75.34"},{"date":"07/22/2019","open":"$75.06"},{"date":"07/19/2019","open":"$74.42"},{"date":"07/18/2019","open":"$74.97"},{"date":"07/17/2019","open":"$78.57"},{"date":"07/16/2019","open":"$75.11"},{"date":"07/15/2019","open":"$75.15"},{"date":"07/12/2019","open":"$74.25"},{"date":"07/11/2019","open":"$74.52"},{"date":"07/10/2019","open":"$76.83"},{"date":"07/09/2019","open":"$76.44"},{"date":"07/08/2019","open":"$75.98"},{"date":"07/05/2019","open":"$74.2"},{"date":"07/03/2019","open":"$77.07"},{"date":"07/02/2019","open":"$77.28"},{"date":"07/01/2019","open":"$80.67"},{"date":"06/28/2019","open":"$75.66"},{"date":"06/27/2019","open":"$75.34"},{"date":"06/26/2019","open":"$73.76"},{"date":"06/25/2019","open":"$73.23"},{"date":"06/24/2019","open":"$72.97"},{"date":"06/21/2019","open":"$72.31"},{"date":"06/20/2019","open":"$73.19"},{"date":"06/19/2019","open":"$72.37"},{"date":"06/18/2019","open":"$69.69"},{"date":"06/17/2019","open":"$69.09"},{"date":"06/14/2019","open":"$68.35"},{"date":"06/13/2019","open":"$69.97"},{"date":"06/12/2019","open":"$69.53"},{"date":"06/11/2019","open":"$71.58"},{"date":"06/10/2019","open":"$69"},{"date":"06/07/2019","open":"$67.69"},{"date":"06/06/2019","open":"$66.92"},{"date":"06/05/2019","open":"$68.04"},{"date":"06/04/2019","open":"$67.61"},{"date":"06/03/2019","open":"$67.09"},{"date":"05/31/2019","open":"$65.78"},{"date":"05/30/2019","open":"$65.97"},{"date":"05/29/2019","open":"$65.36"},{"date":"05/28/2019","open":"$66.64"},{"date":"05/24/2019","open":"$68.93"},{"date":"05/23/2019","open":"$67.02"},{"date":"05/22/2019","open":"$69.13"},{"date":"05/21/2019","open":"$78.91"},{"date":"05/20/2019","open":"$77.95"},{"date":"05/17/2019","open":"$80.49"},{"date":"05/16/2019","open":"$83.79"},{"date":"05/15/2019","open":"$85.55"},{"date":"05/14/2019","open":"$84.27"},{"date":"05/13/2019","open":"$83.24"},{"date":"05/10/2019","open":"$83.38"},{"date":"05/09/2019","open":"$83.37"},{"date":"05/08/2019","open":"$84.85"},{"date":"05/07/2019","open":"$87.2"},{"date":"05/06/2019","open":"$86.33"},{"date":"05/03/2019","open":"$87.76"},{"date":"05/02/2019","open":"$87.5"},{"date":"05/01/2019","open":"$87.17"},{"date":"04/30/2019","open":"$86.98"},{"date":"04/29/2019","open":"$86.4"},{"date":"04/26/2019","open":"$84.51"},{"date":"04/25/2019","open":"$86.17"},{"date":"04/24/2019","open":"$87.04"},{"date":"04/23/2019","open":"$83.9"},{"date":"04/22/2019","open":"$79.83"},{"date":"04/18/2019","open":"$78.72"},{"date":"04/17/2019","open":"$78.82"},{"date":"04/16/2019","open":"$57.46"},{"date":"04/15/2019","open":"$57.14"},{"date":"04/12/2019","open":"$56.28"},{"date":"04/11/2019","open":"$56.44"},{"date":"04/10/2019","open":"$57.71"},{"date":"04/09/2019","open":"$57.57"},{"date":"04/08/2019","open":"$57.79"},{"date":"04/05/2019","open":"$57.98"},{"date":"04/04/2019","open":"$57.75"},{"date":"04/03/2019","open":"$58.2"},{"date":"04/02/2019","open":"$57.98"},{"date":"04/01/2019","open":"$57.64"},{"date":"03/29/2019","open":"$57"},{"date":"03/28/2019","open":"$57.03"},{"date":"03/27/2019","open":"$57.35"},{"date":"03/26/2019","open":"$57.15"},{"date":"03/25/2019","open":"$56.58"},{"date":"03/22/2019","open":"$57.68"},{"date":"03/21/2019","open":"$57.23"},{"date":"03/20/2019","open":"$57.03"},{"date":"03/19/2019","open":"$57.17"},{"date":"03/18/2019","open":"$56.62"},{"date":"03/15/2019","open":"$55"},{"date":"03/14/2019","open":"$55.53"},{"date":"03/13/2019","open":"$55.03"},{"date":"03/12/2019","open":"$54.66"},{"date":"03/11/2019","open":"$53.72"},{"date":"03/08/2019","open":"$53.45"},{"date":"03/07/2019","open":"$54.83"},{"date":"03/06/2019","open":"$53.89"},{"date":"03/05/2019","open":"$53.9"},{"date":"03/04/2019","open":"$54.58"},{"date":"03/01/2019","open":"$54"},{"date":"02/28/2019","open":"$53"},{"date":"02/27/2019","open":"$52.95"},{"date":"02/26/2019","open":"$53.08"},{"date":"02/25/2019","open":"$53.78"},{"date":"02/22/2019","open":"$52.69"},{"date":"02/21/2019","open":"$52.5"},{"date":"02/20/2019","open":"$52.25"},{"date":"02/19/2019","open":"$52"},{"date":"02/15/2019","open":"$52.08"},{"date":"02/14/2019","open":"$51.5"},{"date":"02/13/2019","open":"$52"},{"date":"02/12/2019","open":"$51.3"},{"date":"02/11/2019","open":"$50.55"},{"date":"02/08/2019","open":"$50.24"},{"date":"02/07/2019","open":"$50.83"},{"date":"02/06/2019","open":"$50.94"},{"date":"02/05/2019","open":"$49.73"},{"date":"02/04/2019","open":"$49.71"},{"date":"02/01/2019","open":"$49.58"},{"date":"01/31/2019","open":"$51.2"},{"date":"01/30/2019","open":"$49.68"},{"date":"01/29/2019","open":"$50.49"},{"date":"01/28/2019","open":"$50.32"},{"date":"01/25/2019","open":"$50.93"},{"date":"01/24/2019","open":"$51.95"},{"date":"01/23/2019","open":"$52.92"},{"date":"01/22/2019","open":"$54.97"},{"date":"01/18/2019","open":"$55.39"},{"date":"01/17/2019","open":"$54.97"},{"date":"01/16/2019","open":"$55.75"},{"date":"01/15/2019","open":"$57.32"},{"date":"01/14/2019","open":"$57.02"},{"date":"01/11/2019","open":"$56.47"},{"date":"01/10/2019","open":"$56.19"},{"date":"01/09/2019","open":"$56.26"},{"date":"01/08/2019","open":"$56.71"},{"date":"01/07/2019","open":"$56.39"},{"date":"01/04/2019","open":"$56.5"},{"date":"01/03/2019","open":"$55.95"},{"date":"01/02/2019","open":"$56.2"},{"date":"12/31/2018","open":"$57.12"},{"date":"12/28/2018","open":"$56.33"},{"date":"12/27/2018","open":"$55.54"},{"date":"12/26/2018","open":"$54.25"},{"date":"12/24/2018","open":"$53.7"},{"date":"12/21/2018","open":"$56.26"},{"date":"12/20/2018","open":"$57.22"},{"date":"12/19/2018","open":"$57.54"},{"date":"12/18/2018","open":"$57.69"},{"date":"12/17/2018","open":"$57.59"},{"date":"12/14/2018","open":"$57.56"},{"date":"12/13/2018","open":"$58.14"},{"date":"12/12/2018","open":"$58.44"},{"date":"12/11/2018","open":"$58.45"},{"date":"12/10/2018","open":"$57.77"},{"date":"12/07/2018","open":"$56.61"},{"date":"12/06/2018","open":"$56.01"},{"date":"12/04/2018","open":"$58.99"},{"date":"12/03/2018","open":"$60.51"},{"date":"11/30/2018","open":"$58.22"},{"date":"11/29/2018","open":"$57.89"},{"date":"11/28/2018","open":"$55.89"},{"date":"11/27/2018","open":"$55.59"},{"date":"11/26/2018","open":"$55.79"},{"date":"11/23/2018","open":"$54.77"},{"date":"11/21/2018","open":"$55.21"},{"date":"11/20/2018","open":"$54.2"},{"date":"11/19/2018","open":"$55.85"},{"date":"11/16/2018","open":"$55.12"},{"date":"11/15/2018","open":"$53.83"},{"date":"11/14/2018","open":"$54.84"},{"date":"11/13/2018","open":"$54.74"},{"date":"11/12/2018","open":"$56.37"},{"date":"11/09/2018","open":"$57.78"},{"date":"11/08/2018","open":"$58"},{"date":"11/07/2018","open":"$63.5"},{"date":"11/06/2018","open":"$63.35"},{"date":"11/05/2018","open":"$63.08"},{"date":"11/02/2018","open":"$63.94"},{"date":"11/01/2018","open":"$63.2"},{"date":"10/31/2018","open":"$62.91"},{"date":"10/30/2018","open":"$62.36"},{"date":"10/29/2018","open":"$63.5"},{"date":"10/26/2018","open":"$61.5"},{"date":"10/25/2018","open":"$63.81"},{"date":"10/24/2018","open":"$65.87"},{"date":"10/23/2018","open":"$63.66"},{"date":"10/22/2018","open":"$65.69"},{"date":"10/19/2018","open":"$65.45"},{"date":"10/18/2018","open":"$65.68"},{"date":"10/17/2018","open":"$66.38"},{"date":"10/16/2018","open":"$64.78"},{"date":"10/15/2018","open":"$64.23"},{"date":"10/12/2018","open":"$65.55"},{"date":"10/11/2018","open":"$66.35"},{"date":"10/10/2018","open":"$68.77"},{"date":"10/09/2018","open":"$70.76"},{"date":"10/08/2018","open":"$70.78"},{"date":"10/05/2018","open":"$72.39"},{"date":"10/04/2018","open":"$72"},{"date":"10/03/2018","open":"$73.59"},{"date":"10/02/2018","open":"$72.4"},{"date":"10/01/2018","open":"$72.46"},{"date":"09/28/2018","open":"$71.51"},{"date":"09/27/2018","open":"$72.18"},{"date":"09/26/2018","open":"$72.68"},{"date":"09/25/2018","open":"$72.64"},{"date":"09/24/2018","open":"$73.08"},{"date":"09/21/2018","open":"$74.83"},{"date":"09/20/2018","open":"$74.48"},{"date":"09/19/2018","open":"$75.37"},{"date":"09/18/2018","open":"$73.8"},{"date":"09/17/2018","open":"$74.84"},{"date":"09/14/2018","open":"$74.53"},{"date":"09/13/2018","open":"$73.68"},{"date":"09/12/2018","open":"$72.09"},{"date":"09/11/2018","open":"$71.84"},{"date":"09/10/2018","open":"$70.67"},{"date":"09/07/2018","open":"$69.84"},{"date":"09/06/2018","open":"$70.85"},{"date":"09/05/2018","open":"$69.8"},{"date":"09/04/2018","open":"$68.74"},{"date":"08/31/2018","open":"$67.99"},{"date":"08/30/2018","open":"$68.97"},{"date":"08/29/2018","open":"$69.67"},{"date":"08/28/2018","open":"$68.56"},{"date":"08/27/2018","open":"$67.37"},{"date":"08/24/2018","open":"$67"},{"date":"08/23/2018","open":"$66.98"},{"date":"08/22/2018","open":"$66.22"},{"date":"08/21/2018","open":"$66.09"},{"date":"08/20/2018","open":"$66.33"},{"date":"08/17/2018","open":"$65.5"},{"date":"08/16/2018","open":"$65.86"},{"date":"08/15/2018","open":"$65.14"},{"date":"08/14/2018","open":"$65.09"},{"date":"08/13/2018","open":"$65.15"},{"date":"08/10/2018","open":"$64.65"},{"date":"08/09/2018","open":"$65.1"},{"date":"08/08/2018","open":"$65.21"},{"date":"08/07/2018","open":"$65.93"},{"date":"08/06/2018","open":"$65.86"},{"date":"08/03/2018","open":"$64.74"},{"date":"08/02/2018","open":"$63.96"},{"date":"08/01/2018","open":"$63.55"},{"date":"07/31/2018","open":"$63.83"},{"date":"07/30/2018","open":"$62.65"},{"date":"07/27/2018","open":"$63.22"},{"date":"07/26/2018","open":"$63.05"},{"date":"07/25/2018","open":"$58.55"},{"date":"07/24/2018","open":"$59.35"},{"date":"07/23/2018","open":"$58.4"},{"date":"07/20/2018","open":"$58.98"},{"date":"07/19/2018","open":"$58.71"},{"date":"07/18/2018","open":"$59"},{"date":"07/17/2018","open":"$57.92"},{"date":"07/16/2018","open":"$58.42"},{"date":"07/13/2018","open":"$58.25"},{"date":"07/12/2018","open":"$57.85"},{"date":"07/11/2018","open":"$57.43"},{"date":"07/10/2018","open":"$58.06"},{"date":"07/09/2018","open":"$58.06"},{"date":"07/06/2018","open":"$57.46"},{"date":"07/05/2018","open":"$55.7"},{"date":"07/03/2018","open":"$56.41"},{"date":"07/02/2018","open":"$55.4"},{"date":"06/29/2018","open":"$56.13"},{"date":"06/28/2018","open":"$55.12"},{"date":"06/27/2018","open":"$56.55"},{"date":"06/26/2018","open":"$57.08"},{"date":"06/25/2018","open":"$58.09"},{"date":"06/22/2018","open":"$58.78"},{"date":"06/21/2018","open":"$59.21"},{"date":"06/20/2018","open":"$59.18"},{"date":"06/19/2018","open":"$58.28"},{"date":"06/18/2018","open":"$59.31"},{"date":"06/15/2018","open":"$59.87"},{"date":"06/14/2018","open":"$59.29"},{"date":"06/13/2018","open":"$59.67"},{"date":"06/12/2018","open":"$60.11"},{"date":"06/11/2018","open":"$60.17"},{"date":"06/08/2018","open":"$60.25"},{"date":"06/07/2018","open":"$62"},{"date":"06/06/2018","open":"$59.26"},{"date":"06/05/2018","open":"$58.86"},{"date":"06/04/2018","open":"$58.62"},{"date":"06/01/2018","open":"$58.34"},{"date":"05/31/2018","open":"$58"},{"date":"05/30/2018","open":"$58.41"},{"date":"05/29/2018","open":"$59.5"},{"date":"05/25/2018","open":"$58.85"},{"date":"05/24/2018","open":"$58.58"},{"date":"05/23/2018","open":"$56.91"},{"date":"05/22/2018","open":"$57.91"},{"date":"05/21/2018","open":"$57.68"},{"date":"05/18/2018","open":"$56.93"},{"date":"05/17/2018","open":"$56.49"},{"date":"05/16/2018","open":"$55.76"},{"date":"05/15/2018","open":"$56.5"},{"date":"05/14/2018","open":"$57.33"},{"date":"05/11/2018","open":"$54.76"},{"date":"05/10/2018","open":"$54.45"},{"date":"05/09/2018","open":"$52.86"},{"date":"05/08/2018","open":"$53.04"},{"date":"05/07/2018","open":"$52.58"},{"date":"05/04/2018","open":"$50.18"},{"date":"05/03/2018","open":"$49.99"},{"date":"05/02/2018","open":"$51.24"},{"date":"05/01/2018","open":"$50.76"},{"date":"04/30/2018","open":"$51.25"},{"date":"04/27/2018","open":"$50.75"},{"date":"04/26/2018","open":"$49.52"},{"date":"04/25/2018","open":"$50"},{"date":"04/24/2018","open":"$50.88"},{"date":"04/23/2018","open":"$51.5"},{"date":"04/20/2018","open":"$52.81"},{"date":"04/19/2018","open":"$54"},{"date":"04/18/2018","open":"$55.14"},{"date":"04/17/2018","open":"$54.99"},{"date":"04/16/2018","open":"$55.94"},{"date":"04/13/2018","open":"$56.61"},{"date":"04/12/2018","open":"$55.47"},{"date":"04/11/2018","open":"$54.19"},{"date":"04/10/2018","open":"$54.58"},{"date":"04/09/2018","open":"$53.52"},{"date":"04/06/2018","open":"$54.42"},{"date":"04/05/2018","open":"$55.49"},{"date":"04/04/2018","open":"$53.8"},{"date":"04/03/2018","open":"$54.29"},{"date":"04/02/2018","open":"$55.1"},{"date":"03/29/2018","open":"$55.04"},{"date":"03/28/2018","open":"$54.81"},{"date":"03/27/2018","open":"$56.59"},{"date":"03/26/2018","open":"$54.58"},{"date":"03/23/2018","open":"$55.63"},{"date":"03/22/2018","open":"$56.24"},{"date":"03/21/2018","open":"$57.5"},{"date":"03/20/2018","open":"$58.99"},{"date":"03/19/2018","open":"$60.19"},{"date":"03/16/2018","open":"$60.6"},{"date":"03/15/2018","open":"$60.03"},{"date":"03/14/2018","open":"$59.9"},{"date":"03/13/2018","open":"$59.77"},{"date":"03/12/2018","open":"$63.05"},{"date":"03/09/2018","open":"$62.36"},{"date":"03/08/2018","open":"$62.65"},{"date":"03/07/2018","open":"$61.49"},{"date":"03/06/2018","open":"$63.5"},{"date":"03/05/2018","open":"$64.34"},{"date":"03/02/2018","open":"$64.31"},{"date":"03/01/2018","open":"$65.03"},{"date":"02/28/2018","open":"$66.7"},{"date":"02/27/2018","open":"$67"},{"date":"02/26/2018","open":"$64.55"},{"date":"02/23/2018","open":"$62.81"},{"date":"02/22/2018","open":"$63.15"},{"date":"02/21/2018","open":"$63.12"},{"date":"02/20/2018","open":"$63.01"},{"date":"02/16/2018","open":"$64.77"},{"date":"02/15/2018","open":"$66.38"},{"date":"02/14/2018","open":"$65.15"},{"date":"02/13/2018","open":"$65.23"},{"date":"02/12/2018","open":"$64.89"},{"date":"02/09/2018","open":"$62.95"},{"date":"02/08/2018","open":"$64.63"},{"date":"02/07/2018","open":"$64.22"},{"date":"02/06/2018","open":"$62.31"},{"date":"02/05/2018","open":"$66.3"},{"date":"02/02/2018","open":"$66.18"},{"date":"02/01/2018","open":"$67"},{"date":"01/31/2018","open":"$67.55"},{"date":"01/30/2018","open":"$67.43"},{"date":"01/29/2018","open":"$68.16"},{"date":"01/26/2018","open":"$67.94"},{"date":"01/25/2018","open":"$68.14"},{"date":"01/24/2018","open":"$68.2"},{"date":"01/23/2018","open":"$68.6"},{"date":"01/22/2018","open":"$67.81"},{"date":"01/19/2018","open":"$68.04"},{"date":"01/18/2018","open":"$67.75"},{"date":"01/17/2018","open":"$68.52"},{"date":"01/16/2018","open":"$66.23"},{"date":"01/12/2018","open":"$65.61"},{"date":"01/11/2018","open":"$65.2"},{"date":"01/10/2018","open":"$65.48"},{"date":"01/09/2018","open":"$65.64"},{"date":"01/08/2018","open":"$66.25"},{"date":"01/05/2018","open":"$66.04"},{"date":"01/04/2018","open":"$66.18"},{"date":"01/03/2018","open":"$65.22"},{"date":"01/02/2018","open":"$64.38"},{"date":"12/29/2017","open":"$64.36"},{"date":"12/28/2017","open":"$64.69"},{"date":"12/27/2017","open":"$64.32"},{"date":"12/26/2017","open":"$64.49"},{"date":"12/22/2017","open":"$64.31"},{"date":"12/21/2017","open":"$64.75"},{"date":"12/20/2017","open":"$64.56"},{"date":"12/19/2017","open":"$65.11"},{"date":"12/18/2017","open":"$64.93"},{"date":"12/15/2017","open":"$65.33"},{"date":"12/14/2017","open":"$64.86"},{"date":"12/13/2017","open":"$64.98"},{"date":"12/12/2017","open":"$64.88"},{"date":"12/11/2017","open":"$64.06"},{"date":"12/08/2017","open":"$65.6"},{"date":"12/07/2017","open":"$65.21"},{"date":"12/06/2017","open":"$64.64"},{"date":"12/05/2017","open":"$64.85"},{"date":"12/04/2017","open":"$65.6"},{"date":"12/01/2017","open":"$65.2"},{"date":"11/30/2017","open":"$66.51"},{"date":"11/29/2017","open":"$68.1"},{"date":"11/28/2017","open":"$67.59"},{"date":"11/27/2017","open":"$68.6"}]